roundtrip/__init__.py
roundtrip/manager.py
roundtrip/roundtrip.js
roundtrip/version.py
roundtrip_lib-0.2.1.dist-info/LICENSE
roundtrip_lib-0.2.1.dist-info/METADATA
roundtrip_lib-0.2.1.dist-info/NOTICE
roundtrip_lib-0.2.1.dist-info/WHEEL
roundtrip_lib-0.2.1.dist-info/top_level.txt
roundtrip_lib-0.2.1.dist-info/RECORD
